flutes/__init__.py
flutes/__version__.py
flutes/exception.py
flutes/fs.py
flutes/io.py
flutes/iterator.py
flutes/log.py
flutes/math.py
flutes/multiproc.py
flutes/py.typed
flutes/run.py
flutes/structure.py
flutes/timing.py
flutes/types.py
tests/__init__.py
tests/test_exception.py
tests/test_fs.py
tests/test_io.py
tests/test_iterator.py
tests/test_log.py
tests/test_math.py
tests/test_multiproc.py
tests/test_run.py
tests/test_structure.py
tests/test_timing.py
tests/utils.py
flutes-0.3.0.dist-info/LICENSE
flutes-0.3.0.dist-info/METADATA
flutes-0.3.0.dist-info/WHEEL
flutes-0.3.0.dist-info/top_level.txt
flutes-0.3.0.dist-info/RECORD
