Metadata-Version: 2.1
Name: flutes
Version: 0.3.0
Summary: Utilities to charm your Python
Home-page: https://github.com/huzecong/flutes
Author: Zecong Hu
Author-email: huzecong@gmail.com
License: MIT License
Platform: any
Classifier: Development Status :: 3 - Alpha
Classifier: Intended Audience :: Developers
Classifier: Operating System :: OS Independent
Classifier: License :: OSI Approved :: MIT License
Classifier: Programming Language :: Python :: 3 :: Only
Classifier: Programming Language :: Python :: 3.6
Classifier: Programming Language :: Python :: 3.7
Classifier: Topic :: Utilities
Classifier: Typing :: Typed
Requires-Python: >=3.6
Requires-Dist: ipython
Requires-Dist: psutil
Requires-Dist: termcolor (>=1.0)
Requires-Dist: tqdm (>=4.0)
Requires-Dist: typing-extensions
